llm_ci_runner/__init__.py
llm_ci_runner/__main__.py
llm_ci_runner/core.py
llm_ci_runner/exceptions.py
llm_ci_runner/formatters.py
llm_ci_runner/io_operations.py
llm_ci_runner/llm_execution.py
llm_ci_runner/llm_service.py
llm_ci_runner/logging_config.py
llm_ci_runner/retry.py
llm_ci_runner/schema.py
llm_ci_runner/templates.py
llm_ci_runner-1.5.4.dist-info/METADATA
llm_ci_runner-1.5.4.dist-info/WHEEL
llm_ci_runner-1.5.4.dist-info/entry_points.txt
llm_ci_runner-1.5.4.dist-info/licenses/LICENSE
llm_ci_runner-1.5.4.dist-info/licenses/NOTICE
llm_ci_runner-1.5.4.dist-info/RECORD
