Metadata-Version: 2.4
Name: llm-ci-runner
Version: 1.5.4
Summary: A simple CI/CD utility for running LLM tasks with Semantic Kernel
Project-URL: Homepage, https://technologyworkroom.blogspot.com/2025/06/building-ai-first-devops.html
Project-URL: Repository, https://github.com/Nantero1/ai-first-devops-toolkit
Project-URL: Documentation, https://github.com/Nantero1/ai-first-devops-toolkit
Project-URL: Bug Tracker, https://github.com/Nantero1/ai-first-devops-toolkit/issues
Project-URL: Source, https://github.com/Nantero1/ai-first-devops-toolkit
Project-URL: Changelog, https://github.com/Nantero1/ai-first-devops-toolkit/releases
Author-email: Benjamin Linnik <Benjamin@Linnik.IT>
License: MIT
License-File: LICENSE
License-File: NOTICE
Keywords: ai,automation,azure-openai,ci-cd,devops,llm,semantic-kernel
Classifier: Development Status :: 5 - Production/Stable
Classifier: Intended Audience :: Developers
Classifier: License :: OSI Approved :: MIT License
Classifier: Operating System :: OS Independent
Classifier: Programming Language :: Python :: 3
Classifier: Programming Language :: Python :: 3.10
Classifier: Programming Language :: Python :: 3.11
Classifier: Programming Language :: Python :: 3.12
Classifier: Topic :: Software Development :: Libraries :: Python Modules
Classifier: Topic :: Software Development :: Quality Assurance
Classifier: Topic :: System :: Systems Administration
Classifier: Topic :: Utilities
Requires-Python: >=3.10
Requires-Dist: aiohttp>=3.12.0
Requires-Dist: azure-core>=1.35.0
Requires-Dist: azure-identity>=1.23.0
Requires-Dist: json-schema-to-pydantic>=0.4.0
Requires-Dist: openai>=1.93.0
Requires-Dist: pydantic>=2.11.0
Requires-Dist: rich>=14.0.0
Requires-Dist: ruamel-yaml>=0.18.14
Requires-Dist: semantic-kernel>=1.32.0
Requires-Dist: tenacity>=9.1.2
